hyper/__init__.py
hyper/__version__.py
hyper/coupons.py
hyper/exceptions.py
hyper/licenses.py
hyper/links.py
hyper/products.py
hyper/raffles.py
hyper/client/__init__.py
hyper/client/client.py
hyper/client/core.py
hyper/utils/__init__.py
hyper/utils/helpers.py
hyperco_client-0.1.0.dist-info/LICENSE
hyperco_client-0.1.0.dist-info/METADATA
hyperco_client-0.1.0.dist-info/WHEEL
hyperco_client-0.1.0.dist-info/top_level.txt
hyperco_client-0.1.0.dist-info/RECORD
