Metadata-Version: 2.1
Name: hyperco-client
Version: 0.1.0
Summary: Hyper.co client for Python.
Author: banjo
License: MIT
Keywords: python,client
Classifier: Environment :: Web Environment
Classifier: Intended Audience :: Developers
Classifier: Programming Language :: Python :: 3
Classifier: Operating System :: Unix
Classifier: Operating System :: MacOS :: MacOS X
Classifier: Operating System :: Microsoft :: Windows
License-File: LICENSE
Requires-Dist: requests
